<?xml version="1.0" encoding="UTF-8"?>
<!DOCTYPE products SYSTEM "lab4/course_in.xsd">
<courses>

  <course id="c1">
    <name>Python</name>
    <price>3500.00</price>
    <enrolled>400</enrolled>
    <category>Backend</category>
  </course>

  <course id="c2">
    <name>HTML</name>
    <price>3500.00</price>
    <enrolled>400</enrolled>
    <category>Frontend</category>
  </course>

  <course id="c3">
    <name>Java</name>
    <price>3500.00</price>
    <enrolled>500</enrolled>
    <category>Backend</category>
  </course>

</course>
